mkdocs_bootstrap_elements_plugin/__init__.py
mkdocs_bootstrap_elements_plugin/plugin.py
mkdocs_bootstrap_elements_plugin/css/bootstrap_elements.css
mkdocs_bootstrap_elements_plugin/js/bootstrap_elements.js
mkdocs_bootstrap_elements_plugin-0.1.6.dist-info/METADATA
mkdocs_bootstrap_elements_plugin-0.1.6.dist-info/WHEEL
mkdocs_bootstrap_elements_plugin-0.1.6.dist-info/entry_points.txt
mkdocs_bootstrap_elements_plugin-0.1.6.dist-info/top_level.txt
mkdocs_bootstrap_elements_plugin-0.1.6.dist-info/RECORD
