Metadata-Version: 2.1
Name: mkdocs-bootstrap-elements-plugin
Version: 0.1.6
Summary: A MkDocs plugin that adds Bootstrap accordions, modals, and cards.
Home-page: https://github.com/kdkiss/mkdocs-bootstrap-elements-plugin
Author: Your Name
Author-email: your.email@example.com
License: MIT
Keywords: mkdocs python markdown bootstrap
Classifier: Development Status :: 3 - Alpha
Classifier: Intended Audience :: Developers
Classifier: Intended Audience :: Information Technology
Classifier: License :: OSI Approved :: MIT License
Classifier: Programming Language :: Python
Classifier: Programming Language :: Python :: 3 :: Only
Classifier: Programming Language :: Python :: 3.6
Classifier: Programming Language :: Python :: 3.7
Classifier: Programming Language :: Python :: 3.8
Classifier: Programming Language :: Python :: 3.9
Requires-Python: >=3.6
Requires-Dist: mkdocs>=1.0.4
